advanced_quotes/__init__.py
advanced_quotes/authors.py
advanced_quotes/misc.py
advanced_quotes/quotes.py
advanced_quotes/topics.py
advanced_quotes-1.0.1.dist-info/LICENSE
advanced_quotes-1.0.1.dist-info/METADATA
advanced_quotes-1.0.1.dist-info/WHEEL
advanced_quotes-1.0.1.dist-info/top_level.txt
advanced_quotes-1.0.1.dist-info/RECORD
