Metadata-Version: 2.1
Name: advanced-quotes
Version: 1.0.1
Summary: Your all-access pass to the world's largest quotations database. Random , daily quotes , over 40 thousand authors, various topics. Inside your comfy python development environment!
Home-page: https://github.com/Mahdios/advanced_quotes
Author: Mahdi Djaber
Author-email: mahdios.dj@gmail.com
License: GPL-3.0
Platform: UNKNOWN
Requires-Dist: bs4
Requires-Dist: requests
